pixelti/__init__.py
pixelti/cli.py
pixelti/core.py
pixelti/display.py
pixelti/pallette.py
pixelti/version.py
pixelti/app/cli/generate_pixelti.py
pixelti/assets/pallettes/arne-199x.hex
pixelti/assets/pallettes/autumn-thanksgiving-meal.hex
pixelti/assets/pallettes/cc-29.hex
pixelti/assets/pallettes/miyazaki-16.hex
pixelti/lib/__init__.py
pixelti/lib/utils.py
pixelti-0.1.0a11.dist-info/METADATA
pixelti-0.1.0a11.dist-info/WHEEL
pixelti-0.1.0a11.dist-info/top_level.txt
pixelti-0.1.0a11.dist-info/RECORD
