Metadata-Version: 2.1
Name: pixelti
Version: 0.1.0a11
Summary: A pixel art creation tool
Home-page: https://github.com/titancodehub/pixelti
Author: titanabrian
Keywords: pixel,art,creative
Classifier: Programming Language :: Python :: 3
Requires-Dist: Colr ==0.9.1
Requires-Dist: numpy ==1.26.2
Requires-Dist: Pillow ==10.1.0
Requires-Dist: setuptools ==68.2.2
Requires-Dist: typer ==0.9.0
Requires-Dist: typing-extensions ==4.8.0
Requires-Dist: validators ==0.22.0
